{
  "main": {
    "id": "22003e5a1fd9c039",
    "type": "split",
    "children": [
      {
        "id": "27de7e116694b0b7",
        "type": "tabs",
        "children": [
          {
            "id": "24177a6481828f9b",
            "type": "leaf",
            "state": {
              "type": "markdown",
              "state": {
                "file": "00. Вопросы по курсу АЭВМ 2025.md",
                "mode": "source",
                "source": false
              },
              "icon": "lucide-file",
              "title": "00. Вопросы по курсу АЭВМ 2025"
            }
          }
        ]
      }
    ],
    "direction": "vertical"
  },
  "left": {
    "id": "d344cd0afccc9cf1",
    "type": "split",
    "children": [
      {
        "id": "8668b60486bdd8ff",
        "type": "tabs",
        "children": [
          {
            "id": "f098fdd95c45654d",
            "type": "leaf",
            "state": {
              "type": "file-explorer",
              "state": {
                "sortOrder": "alphabetical",
                "autoReveal": false
              },
              "icon": "lucide-folder-closed",
              "title": "Файловый менеджер"
            }
          },
          {
            "id": "b582c42542ad898a",
            "type": "leaf",
            "state": {
              "type": "search",
              "state": {
                "query": "",
                "matchingCase": false,
                "explainSearch": false,
                "collapseAll": false,
                "extraContext": false,
                "sortOrder": "alphabetical"
              },
              "icon": "lucide-search",
              "title": "Поиск"
            }
          },
          {
            "id": "73947ad422640c11",
            "type": "leaf",
            "state": {
              "type": "bookmarks",
              "state": {},
              "icon": "lucide-bookmark",
              "title": "Закладки"
            }
          }
        ]
      }
    ],
    "direction": "horizontal",
    "width": 300
  },
  "right": {
    "id": "89989332f9d6c160",
    "type": "split",
    "children": [
      {
        "id": "8922bc959feb3c13",
        "type": "tabs",
        "children": [
          {
            "id": "5e72bc25b83ac9bf",
            "type": "leaf",
            "state": {
              "type": "backlink",
              "state": {
                "file": "00. Вопросы по курсу АЭВМ 2025.md",
                "collapseAll": false,
                "extraContext": false,
                "sortOrder": "alphabetical",
                "showSearch": false,
                "searchQuery": "",
                "backlinkCollapsed": false,
                "unlinkedCollapsed": true
              },
              "icon": "links-coming-in",
              "title": "Обратные ссылки для 00. Вопросы по курсу АЭВМ 2025"
            }
          },
          {
            "id": "9e0d84c6763b8e00",
            "type": "leaf",
            "state": {
              "type": "outgoing-link",
              "state": {
                "file": "00. Вопросы по курсу АЭВМ 2025.md",
                "linksCollapsed": false,
                "unlinkedCollapsed": true
              },
              "icon": "links-going-out",
              "title": "Исходящие ссылки из 00. Вопросы по курсу АЭВМ 2025"
            }
          },
          {
            "id": "2dd3d0eada95242c",
            "type": "leaf",
            "state": {
              "type": "tag",
              "state": {
                "sortOrder": "frequency",
                "useHierarchy": true,
                "showSearch": false,
                "searchQuery": ""
              },
              "icon": "lucide-tags",
              "title": "Теги"
            }
          },
          {
            "id": "78135f7f1f51c7b1",
            "type": "leaf",
            "state": {
              "type": "outline",
              "state": {
                "file": "00. Вопросы по курсу АЭВМ 2025.md",
                "followCursor": false,
                "showSearch": false,
                "searchQuery": ""
              },
              "icon": "lucide-list",
              "title": "Структура 00. Вопросы по курсу АЭВМ 2025"
            }
          }
        ]
      }
    ],
    "direction": "horizontal",
    "width": 300,
    "collapsed": true
  },
  "left-ribbon": {
    "hiddenItems": {
      "switcher:Меню быстрого перехода": false,
      "graph:Граф": false,
      "canvas:Создать новый холст": false,
      "daily-notes:Сегодняшняя заметка": false,
      "templates:Вставить шаблон": false,
      "command-palette:Открыть палитру команд": false
    }
  },
  "active": "24177a6481828f9b",
  "lastOpenFiles": [
    "Основные подходы к построению многопроцессорных систем..md",
    "00. Вопросы по курсу АЭВМ 2025.md",
    "Принципы программного управления.md",
    "Особенности построения систем нечувствительных к отказам (Fault-Tolerance) и систем высокой доступности High Availability.md",
    "Память ЭВМ.md",
    "Параллельное выполнение команд, проблемы и пути решения. Суперскалярная архитектура процессора.md",
    "Первоисточник.md",
    "Подключение регистров к системной шине..md",
    "Построение отказоустойчивых кластеров..md"
  ]
}